juspay/Cards.py
juspay/Customers.py
juspay/JuspayException.py
juspay/Orders.py
juspay/Payments.py
juspay/SampleTest.py
juspay/Test.py
juspay/Wallets.py
juspay/__init__.py
juspay/config.py
juspay/util.py
juspay-1.1.3.dist-info/METADATA
juspay-1.1.3.dist-info/WHEEL
juspay-1.1.3.dist-info/top_level.txt
juspay-1.1.3.dist-info/RECORD
