Metadata-Version: 2.1
Name: juspay
Version: 1.1.3
Summary: Python client for JusPay Express Checkout API
Home-page: https://www.juspay.in 
Author: JusPay
Author-email: ninjas@juspay.in
License: MIT
Keywords: juspay expresscheckout payments
Platform: UNKNOWN
Classifier: Development Status :: 4 - Beta
Classifier: Intended Audience :: Developers
Classifier: License :: OSI Approved :: MIT License
Classifier: Programming Language :: Python :: 2
Classifier: Programming Language :: Python :: 2.6
Classifier: Programming Language :: Python :: 2.7
Classifier: Programming Language :: Python :: 3
Classifier: Programming Language :: Python :: 3.3
Classifier: Programming Language :: Python :: 3.4
Classifier: Programming Language :: Python :: 3.5
Requires-Dist: requests
